README.rst
setup.py
bjarkan/__init__.py
bjarkan/agent.py
bjarkan/cli.py
bjarkan/device_manager.py
bjarkan/list_devices.py
bjarkan.egg-info/PKG-INFO
bjarkan.egg-info/SOURCES.txt
bjarkan.egg-info/dependency_links.txt
bjarkan.egg-info/entry_points.txt
bjarkan.egg-info/top_level.txt