Metadata-Version: 1.1
Name: bjarkan
Version: 1.1.9
Summary: Bluetooth command line utility
Home-page: https://github.com/willdeberry/bjarkan
Author: GetWellNetwork
Author-email: willdeberry@gmail.com
License: Copyright 2016 GetWellNetwork, Inc., BSD copyright and disclaimer apply
Download-URL: https://github.com/willdeberry/bjarkan
Keywords: bluez bluetooth cli
Platform: UNKNOWN
Classifier: Programming Language :: Python
Classifier: Programming Language :: Python :: 3
Classifier: Programming Language :: Python :: 3.4
Classifier: Programming Language :: Python :: 3.5
Classifier: Programming Language :: Python :: 3.6
Classifier: License :: OSI Approved :: BSD License
Classifier: Operating System :: POSIX
Classifier: Environment :: Console
Classifier: Intended Audience :: End Users/Desktop
Classifier: Intended Audience :: Developers
Classifier: Intended Audience :: System Administrators
